setup.py
currency_calculator/PyCurrency.py
currency_calculator/__init__.py
currency_calculator.egg-info/PKG-INFO
currency_calculator.egg-info/SOURCES.txt
currency_calculator.egg-info/dependency_links.txt
currency_calculator.egg-info/top_level.txt