Metadata-Version: 1.1
Name: currency-calculator
Version: 0.1.1
Summary: A library to convert currency.
Home-page: https://github.com/764664/PyCurrency
Author: Jie Lu
Author-email: jielu@msn.com
License: UNKNOWN
Download-URL: https://github.com/764664/PyCurrency
Keywords: currency
Platform: UNKNOWN
